src/__init__.py
src/auth.py
src/config.py
src/db.py
src/mcp_transport.py
src/models.py
src/rlm_engine.py
src/server.py
src/usage.py
src/services/__init__.py
src/services/agent_limits.py
src/services/agent_memory.py
src/services/cache.py
src/services/chunker.py
src/services/embeddings.py
src/services/indexer.py
src/services/shared_context.py
src/services/swarm_coordinator.py
src/services/swarm_events.py
tests/__init__.py
tests/test_context_query.py
tests/test_server.py
snipara_fastapi-1.9.0.dist-info/METADATA
snipara_fastapi-1.9.0.dist-info/WHEEL
snipara_fastapi-1.9.0.dist-info/entry_points.txt
snipara_fastapi-1.9.0.dist-info/licenses/LICENSE
snipara_fastapi-1.9.0.dist-info/RECORD
