Metadata-Version: 2.3
Name: snipara-fastapi
Version: 1.9.0
Summary: Hosted MCP server for Snipara - Context optimization and Agent infrastructure for LLMs
Author: RLM SaaS Team
License: MIT
License-File: LICENSE
Requires-Python: >=3.11
Requires-Dist: bcrypt>=4.1.0
Requires-Dist: fastapi>=0.109.0
Requires-Dist: httpx>=0.26.0
Requires-Dist: numpy>=1.24.0
Requires-Dist: prisma>=0.12.0
Requires-Dist: pydantic-settings>=2.1.0
Requires-Dist: pydantic>=2.5.0
Requires-Dist: python-dotenv>=1.0.0
Requires-Dist: redis>=5.0.0
Requires-Dist: sentence-transformers>=2.2.0
Requires-Dist: sentry-sdk[fastapi]>=1.40.0
Requires-Dist: tiktoken>=0.5.0
Requires-Dist: uvicorn[standard]>=0.27.0
Provides-Extra: benchmark
Requires-Dist: anthropic>=0.40.0; extra == 'benchmark'
Requires-Dist: tiktoken>=0.5.0; extra == 'benchmark'
Provides-Extra: dev
Requires-Dist: httpx>=0.26.0; extra == 'dev'
Requires-Dist: mypy>=1.8.0; extra == 'dev'
Requires-Dist: pytest-asyncio>=0.23.0; extra == 'dev'
Requires-Dist: pytest-cov>=4.1.0; extra == 'dev'
Requires-Dist: pytest>=7.4.0; extra == 'dev'
Requires-Dist: ruff>=0.1.0; extra == 'dev'
